speechrec/__init__.py
speechrec/exceptions.py
speechrec/faster_whisper.py
speechrec/file_utils.py
speechrec/model_base.py
speechrec/whisper.py
speechreclib-0.3.0.dist-info/METADATA
speechreclib-0.3.0.dist-info/WHEEL
speechreclib-0.3.0.dist-info/RECORD
