Metadata-Version: 2.4
Name: speechreclib
Version: 0.3.0
Summary: 
Author: avdonin.pb@yandex.ru
Requires-Python: >=3.10,<3.14
Classifier: Programming Language :: Python :: 3
Classifier: Programming Language :: Python :: 3.10
Classifier: Programming Language :: Python :: 3.11
Classifier: Programming Language :: Python :: 3.12
Classifier: Programming Language :: Python :: 3.13
Provides-Extra: cpu
Provides-Extra: dev
Provides-Extra: gpu
Requires-Dist: faster-whisper (>=1.2.0,<2.0.0)
Requires-Dist: openai-whisper (>=20250625,<20250626)
Requires-Dist: pytest (>=8.4.2,<9.0.0) ; extra == "dev"
Requires-Dist: pytest-cov (>=7.0.0,<8.0.0) ; extra == "dev"
Requires-Dist: soundfile (>=0.13.1,<0.14.0)
Requires-Dist: torch (==2.8.0+cpu) ; extra == "cpu"
Requires-Dist: torch (>=2.8.0,<3.0.0) ; extra == "gpu"
Requires-Dist: torchaudio (==2.8.0+cpu) ; extra == "cpu"
Requires-Dist: torchaudio (>=2.8.0,<3.0.0) ; extra == "gpu"
Requires-Dist: tox (>=4.0.0,<5.0.0) ; extra == "dev"
Requires-Dist: transformers (>=4.56.2,<5.0.0)
